reddit_searcher.py
web_content_parser-1.0.0.dist-info/licenses/LICENSE
web_content_parser-1.0.0.dist-info/METADATA
web_content_parser-1.0.0.dist-info/WHEEL
web_content_parser-1.0.0.dist-info/top_level.txt
web_content_parser-1.0.0.dist-info/RECORD
